{"LoginRequest":0,"LoginStatus":1,"LoginSuccess":2,"Ping":3,"PlayerSpawn":4,"PlayerKick":5,"PlayerEntity":6,"PlayerTeleport":7,"PlayerInventory":8,"PlayerSlotUpdate":9,"PlayerApplyImpulse":10,"PlayerUpdateMovement":11,"PlayerUpdatePhysics":12,"PlayerHealth":13,"PlayerSetBlockReach":14,"PlayerOpenInventory":15,"PlayerUpdateOpenInventory":16,"SoundPlay":17,"ChatMessage":18,"UpdateTextBoard":19,"EntityCreate":20,"EntityRemove":21,"EntityMove":22,"EntityNameUpdate":23,"EntityHeldItem":24,"EntityArmor":25,"EntityAnimate":26,"WorldBlockUpdate":27,"WorldMultiBlockUpdate":28,"WorldChunkLoad":29,"WorldChunkUnload":30,"WorldChunkIsLoaded":31,"WorldChunksRemoveAll":32,"EnvironmentFogUpdate":33,"EnvironmentSkyUpdate":34,"EnvironmentSetSkybox":35,"PluginMessage":36,"ChatComponentType":37,"BasicChatComponentType":38,"Item":39,"InventoryType":40,"ContainerType":41,"MouseClickType":42}